setup.py
FileGen/__init__.py
FileGenerator.egg-info/PKG-INFO
FileGenerator.egg-info/SOURCES.txt
FileGenerator.egg-info/dependency_links.txt
FileGenerator.egg-info/entry_points.txt
FileGenerator.egg-info/not-zip-safe
FileGenerator.egg-info/requires.txt
FileGenerator.egg-info/top_level.txt