Metadata-Version: 1.0
Name: FileGenerator
Version: 1.0.2
Summary: Universal file generation toolbox
Home-page: http://josiahkerley.github.io/projects/2016/06/18/filegen.html
Author: Josiah Kerley
Author-email: josiah@kerley.io
License: UNKNOWN
Platform: UNKNOWN
